[
{"name": "EPIC-long", 
 "desc": "EPIC subjects that have at least 10 T1w scans over 10 years",
 "msid_path": "/data/henry6/mindcontrol_ucsf_env/watchlists/msid/EPIC.txt",
 "modality": "T1",
 "to_ignore":  ["Ax_3D_SPGR", "Ax_FSPGR_BRAVO", "Ax_FSPGR_BRAVO_REPOSITION", "t1_fl3d_sag_p2_iso_1.0"],
 "reduction": "long",
 "modality_reduction": true,
 "num_timepoints": 10,
 "num_years": 10},
 {"name": "VEO",
 "desc": "Project VEO: Superawesome Visualization",
 "msid_path": "/data/henry6/mindcontrol_ucsf_env/watchlists/msid/VEO.txt",
 "modality": "T1",
 "to_ignore":  ["Ax_3D_SPGR", "Ax_FSPGR_BRAVO", "Ax_FSPGR_BRAVO_REPOSITION", "t1_fl3d_sag_p2_iso_1.0", "T1_AX"],
 "reduction": null,
 "modality_reduction":true},
 {"name": "VEO_flair",
 "desc": "Project VEO: Superawesome Visualization",
 "msid_path": "/data/henry6/mindcontrol_ucsf_env/watchlists/msid/VEO.txt",
 "modality": "FLAIR",
 "to_ignore":  [],
 "reduction": null,
 "modality_reduction":true},
 {"name": "bioscreen",
 "desc": "Bioscreen Trial",
 "msid_path": "/data/henry6/mindcontrol_ucsf_env/watchlists/msid/bioscreen.txt",
 "modality": "T1",
 "to_ignore":  [],
 "reduction": null,
 "modality_reduction":true},
{"name": "Genentech",
 "desc": "Genentech",
 "msid_path": "/data/henry6/mindcontrol_ucsf_env/watchlists/msid/genentech.txt",
 "modality": "T1",
 "to_ignore":  [],
 "reduction": null,
 "modality_reduction": true},
{"name" : "tumor_pilot_prepost",
"desc" : "pilot_prepost_tumor",
"msid_path" : "/data/henry6/mindcontrol_ucsf_env/watchlists/msid/tumor_pilot_prepost.txt",
"modality" : null,
"to_ignore" : [],
"reduction" : null,
"modality_reduction":false},
{"name" : "tumor_all",
"desc" : "all_tumor_pts_in_MSPACMAN)_as_of_090216",
"msid_path" : "/data/henry6/mindcontrol_ucsf_env/watchlists/msid/tumor_all.txt",
"modality" : null,
"to_ignore" : [],
"reduction" : null,
"modality_reduction":false}
]
